wagtail_mautic/__init__.py
wagtail_mautic/admin.py
wagtail_mautic/apps.py
wagtail_mautic/models.py
wagtail_mautic/tests.py
wagtail_mautic/views.py
wagtail_mautic/migrations/0001_initial.py
wagtail_mautic/migrations/0002_auto_20200914_1952.py
wagtail_mautic/migrations/__init__.py
wagtail_mautic/templates/wagtail_mautic/mautic_prefetch.html
wagtail_mautic/templates/wagtail_mautic/mautic_tracking.html
wagtail_mautic/templatetags/mautic_tags.py
wagtail_mautic-0.2.1.dist-info/LICENSE
wagtail_mautic-0.2.1.dist-info/WHEEL
wagtail_mautic-0.2.1.dist-info/METADATA
wagtail_mautic-0.2.1.dist-info/RECORD
