Metadata-Version: 2.1
Name: wagtail_mautic
Version: 0.2.1
Summary: Adds Mautic Marketing Automation into a Wagtail site with a few simple template tags
Home-page: https://github.com/ttamg/wagtail-mautic
License: UNKNOWN
Keywords: wagtail, mautic
Author: Matt Gosden
Author-email: mdgosden@gmail.com
Requires-Python: >=3.6
Classifier: License :: OSI Approved :: MIT License
Classifier: Intended Audience :: Developers
Classifier: Programming Language :: Python :: 3 :: Only
Requires-Dist: wagtail>=2.8
Requires-Dist: django>=2.10
